pinax/__init__.py
pinax/referrals/__init__.py
pinax/referrals/admin.py
pinax/referrals/apps.py
pinax/referrals/callbacks.py
pinax/referrals/conf.py
pinax/referrals/middleware.py
pinax/referrals/models.py
pinax/referrals/signals.py
pinax/referrals/urls.py
pinax/referrals/utils.py
pinax/referrals/views.py
pinax/referrals/migrations/0001_initial.py
pinax/referrals/migrations/0002_auto_20180130_0904.py
pinax/referrals/migrations/0003_auto_20190918_1831.py
pinax/referrals/migrations/0004_referralresponse_http_referrer.py
pinax/referrals/migrations/__init__.py
pinax/referrals/templates/pinax/referrals/_create_referral_form.html
pinax/referrals/templatetags/__init__.py
pinax/referrals/templatetags/pinax_referrals_tags.py
pinax/referrals/tests/__init__.py
pinax/referrals/tests/test_models.py
pinax/referrals/tests/tests.py
pinax/referrals/tests/urls.py
pinax_referrals-4.3.0.dist-info/AUTHORS
pinax_referrals-4.3.0.dist-info/LICENSE
pinax_referrals-4.3.0.dist-info/METADATA
pinax_referrals-4.3.0.dist-info/WHEEL
pinax_referrals-4.3.0.dist-info/top_level.txt
pinax_referrals-4.3.0.dist-info/RECORD
